hojulian/cdk_pipelines_github/__init__.py
hojulian/cdk_pipelines_github/py.typed
hojulian/cdk_pipelines_github/_jsii/__init__.py
hojulian/cdk_pipelines_github/_jsii/cdk-pipelines-github@0.0.9.jsii.tgz
hojulian.cdk_pipelines_github-0.0.9.dist-info/LICENSE
hojulian.cdk_pipelines_github-0.0.9.dist-info/METADATA
hojulian.cdk_pipelines_github-0.0.9.dist-info/NOTICE
hojulian.cdk_pipelines_github-0.0.9.dist-info/WHEEL
hojulian.cdk_pipelines_github-0.0.9.dist-info/top_level.txt
hojulian.cdk_pipelines_github-0.0.9.dist-info/RECORD
