Metadata-Version: 2.1
Name: hojulian.cdk-pipelines-github
Version: 0.0.9
Summary: GitHub Workflows support for CDK Pipelines
Home-page: https://github.com/hojulian/cdk-pipelines-github.git
Author: Amazon Web Services<aws-cdk-dev@amazon.com>
License: Apache-2.0
Project-URL: Source, https://github.com/hojulian/cdk-pipelines-github.git
Classifier: Intended Audience :: Developers
Classifier: Operating System :: OS Independent
Classifier: Programming Language :: JavaScript
Classifier: Programming Language :: Python :: 3 :: Only
Classifier: Programming Language :: Python :: 3.8
Classifier: Programming Language :: Python :: 3.9
Classifier: Programming Language :: Python :: 3.10
Classifier: Programming Language :: Python :: 3.11
Classifier: Typing :: Typed
Classifier: Development Status :: 4 - Beta
Classifier: License :: OSI Approved
Requires-Python: ~=3.8
License-File: LICENSE
License-File: NOTICE
Requires-Dist: aws-cdk-lib <3.0.0,>=2.80.0
Requires-Dist: constructs <11.0.0,>=10.0.46
Requires-Dist: jsii <2.0.0,>=1.95.0
Requires-Dist: publication >=0.0.3
Requires-Dist: typeguard ~=2.13.3
